snappy/__init__.py
snappy/snappy.py
snappy/src/generate_output.py
snappy/src/main_stream.py
snappy/src/methods.py
snappy/src/seq_processing.py
ont_snappy-0.1.1.dist-info/LICENSE
ont_snappy-0.1.1.dist-info/METADATA
ont_snappy-0.1.1.dist-info/WHEEL
ont_snappy-0.1.1.dist-info/entry_points.txt
ont_snappy-0.1.1.dist-info/top_level.txt
ont_snappy-0.1.1.dist-info/RECORD
