Metadata-Version: 2.1
Name: ont-snappy
Version: 0.1.1
Summary: Nanopore-based methylation sites caller
Home-page: https://github.com/DNKonanov/ont-snappy
Author: D.N. Konanov
Author-email: konanovdmitriy@gmail.com
Project-URL: Bug Tracker, https://github.com/DNKonanov/ont-snappy
Classifier: Programming Language :: Python :: 3
Classifier: License :: OSI Approved :: MIT License
Classifier: Operating System :: OS Independent
Requires-Python: >=3.7
License-File: LICENSE
Requires-Dist: biopython
Requires-Dist: matplotlib
Requires-Dist: scipy
Requires-Dist: seaborn
Requires-Dist: tqdm
Requires-Dist: polars
Requires-Dist: pandas
